LICENSE
MANIFEST.in
README.rst
requirements-devel.txt
requirements.txt
setup.cfg
setup.py
finch/__init__.py
finch/auth.py
finch/collection.py
finch/errors.py
finch/session.py
finch.egg-info/PKG-INFO
finch.egg-info/SOURCES.txt
finch.egg-info/dependency_links.txt
finch.egg-info/requires.txt
finch.egg-info/top_level.txt