Metadata-Version: 1.1
Name: finch
Version: 0.3.3
Summary: Asynchronous RESTful API consumer for Python
Home-page: UNKNOWN
Author: Jaime Gil de Sagredo Luna
Author-email: jaimegildesagredo@gmail.com
License: UNKNOWN
Platform: UNKNOWN
Classifier: Development Status :: 3 - Alpha
Classifier: Intended Audience :: Developers
Classifier: Natural Language :: English
Classifier: Operating System :: OS Independent
Classifier: Programming Language :: Python
Classifier: Topic :: Software Development :: Libraries :: Python Modules
